wx_robot/__init__.py
wx_robot/bin.py
wx_robot/core.py
wx_robot/util.py
wx_robot/version.json
wx_robot_client-1.0.1.dist-info/METADATA
wx_robot_client-1.0.1.dist-info/WHEEL
wx_robot_client-1.0.1.dist-info/entry_points.txt
wx_robot_client-1.0.1.dist-info/top_level.txt
wx_robot_client-1.0.1.dist-info/RECORD
